[
    {
        "id": "686d0bcfd3791",
        "token": "0bskkfXwc3VSYBBkLPy7Y2D8IBGPjZ",
        "timestamp": "2025-07-08T12:15:10.221Z",
        "source": "website",
        "uuid": "629cb2bc-cb6e-4f82-a274-2883fc212bb1"
    },
    {
        "id": "686d12d537b6b",
        "token": "x0mEsuWJaC2ZSL6lAf6iRDofZRxMfb",
        "timestamp": "2025-07-08T12:45:07.712Z",
        "source": "website",
        "uuid": "8af2e6c4-4d9f-436d-8ad3-390f5960b16a"
    },
    {
        "id": "686d1b5116b91",
        "token": "EMuPtpImVPZdR7uEyxJ8syQkgNQpmS",
        "timestamp": "2025-07-08T13:21:19.425Z",
        "source": "website",
        "uuid": "930a5ac2-d099-4287-b78a-8900c24ac1ad"
    },
    {
        "id": "686d1c953caf7",
        "token": "KYlKVQtKeUJKGJlVPlJspsmRaB5kmQ",
        "timestamp": "2025-07-08T13:26:44.218Z",
        "source": "website",
        "uuid": "2f8e3c15-4494-47a9-84f8-d3839b5a18ed"
    }
]