[
    {
        "id": "68642eb34ce9d",
        "token": "d0a7f0d4654b8f4d2d793e6c4c952fcc",
        "timestamp": "2025-07-01T18:53:26.321Z",
        "source": "shortlink",
        "uuid": "ecb39cce-21a7-4e63-8b63-c70ce180f4ab",
        "expires_at": "2025-07-01T20:53:26Z"
    },
    {
        "id": "68642f2f3e9e8",
        "token": "1e9656d24587d0c63aa4b926648eb9f0",
        "timestamp": "2025-07-01T18:55:26.229Z",
        "source": "shortlink",
        "uuid": "5a6e0ea9-3644-4ac6-a830-ba752cdb8a60",
        "expires_at": "2025-07-01T20:55:26Z"
    },
    {
        "id": "68643e9580ea9",
        "token": "e1ca691337655c5c1596388a038f16cc",
        "timestamp": "2025-07-01T20:01:16.380Z",
        "source": "shortlink",
        "uuid": "53dd3698-bbab-413b-a914-25281dcc8276",
        "expires_at": "2025-07-01T22:01:16Z"
    },
    {
        "id": "6864499f3c6f4",
        "token": "JemXhIxf5TIbrZmwANLTDLMdMsRGRA",
        "timestamp": "2025-07-01T20:48:31.012Z",
        "source": "website",
        "uuid": "65036553-0033-4a14-8fc9-d224e0594220"
    }
]