[
    {
        "id": "686329be065db",
        "token": "712b7c3adc6db5e9ec2bf54040af85d9",
        "timestamp": "2025-07-01T00:20:00.762Z",
        "source": "shortlink",
        "uuid": "4ee5bbad-d68a-4de3-a4c8-a1a846dd61aa",
        "expires_at": "2025-07-01T02:20:00Z"
    },
    {
        "id": "4493a9e4314d4",
        "token": "tFLz8kzFLm9u07Ie0AjEAssRCaSOcU",
        "timestamp": "2025-07-01T00:52:17Z",
        "source": "telegram",
        "uuid": "ef93b804-2295-480c-9d0e-6a10659a0108",
        "githubSignature": "762ee31a1e732f2c8ee609d8d1c03a458c634cb94445dff0973f181cdf7efbdd"
    },
    {
        "id": "68633bf2d9e99",
        "token": "427b40c9da64f1b275d0863b378495c1",
        "timestamp": "2025-07-01T01:37:41.286Z",
        "source": "shortlink",
        "uuid": "e819a2af-3a90-4de5-bd68-2ca6ce96e3dd",
        "expires_at": "2025-07-01T03:37:41Z"
    },
    {
        "id": "6863428637b73",
        "token": "3a20fa61b62fb09e7167bd62341d95ee",
        "timestamp": "2025-07-01T02:05:43.925Z",
        "source": "shortlink",
        "uuid": "bb9efc2f-c198-4bdb-ab0a-6e22ca34d012",
        "expires_at": "2025-07-01T04:05:43Z"
    },
    {
        "id": "68634772a6088",
        "token": "6f7XnhthAMbmBu8jgKb9eNzj6H1Lxd",
        "timestamp": "2025-07-01T02:26:57.104Z",
        "source": "website",
        "uuid": "03485dae-afcc-4cf7-9257-4165dcb3fb26"
    },
    {
        "id": "68634bb945a6e",
        "token": "7mAihj1zYXj0sYLRIASgQ0gzlJZ3oE",
        "timestamp": "2025-07-01T02:45:12.376Z",
        "source": "website",
        "uuid": "51531d9f-155e-43fd-ab67-34a2a297734d"
    },
    {
        "id": "68634dde6a136",
        "token": "1jup1BGPu4TbsCldW59hHkeXIIusRh",
        "timestamp": "2025-07-01T02:54:21.529Z",
        "source": "website",
        "uuid": "ead23501-450d-401b-af56-cdae28a4661b"
    }
]