[
    {
        "token": "ef3a08f723c491a10da1e305cd030635",
        "timestamp": "2025-08-23T00:16:44Z",
        "uuid": "b0531dc1-b796-490e-9dc2-ca396bc5ea6d",
        "watch_time": 120,
        "video_id": "KnSsOhC6C34",
        "ip_address": "103.227.148.104",
        "user_agent": "Mozilla/5.0 (Linux; Android 10; K) AppleWebKit/537.36 (KHTML, like Gecko) Chrome/139.0.0.0 Safari/537.36",
        "pow_verified": true,
        "request_count": 0,
        "session_hash": "588a151fdbcb48388b72809e921f03078f7e1bd56ee7300450471b71b5168cdc",
        "id": "68a9086cc1ed0",
        "source": "website"
    },
    {
        "id": "68a9146fce418",
        "token": "c074708c45adee64e1019048cbfd48ec",
        "timestamp": "2025-08-23T01:07:49.380Z",
        "source": "shortlink",
        "uuid": "fd3d3345-02dc-42af-8a3f-899260d08aaf",
        "expires_at": "2025-08-23T03:07:49Z"
    },
    {
        "token": "678970b45940f39f1deb30c878e2fc7c",
        "timestamp": "2025-08-23T01:41:28Z",
        "uuid": "f3505778-034b-463c-9b5a-b71e595e6162",
        "watch_time": 300,
        "video_id": "ky2YLjJhEWs",
        "ip_address": "1.179.41.160",
        "user_agent": "Mozilla/5.0 (Linux; Android 10; K) AppleWebKit/537.36 (KHTML, like Gecko) Chrome/139.0.0.0 Mobile Safari/537.36",
        "pow_verified": true,
        "request_count": 0,
        "session_hash": "787ce82137bce8f669fde334f566ab789d28529b1955a7bb5e2c40d78bff0f28",
        "id": "68a91c487009d",
        "source": "website"
    },
    {
        "token": "66d619c17457f636a11fea9de8ccc655",
        "timestamp": "2025-08-23T02:07:21Z",
        "uuid": "4b34dfff-be82-4059-a288-80ee9a27124f",
        "watch_time": 240,
        "video_id": "JSGebCw9Ltc",
        "ip_address": "180.248.33.209",
        "user_agent": "Mozilla/5.0 (Linux; Android 10; K) AppleWebKit/537.36 (KHTML, like Gecko) Chrome/139.0.0.0 Mobile Safari/537.36",
        "pow_verified": true,
        "request_count": 0,
        "session_hash": "185500f033b809f1353039d982b5f65ed1d3035ee03602379ca56e2113257600",
        "id": "68a9225a28762",
        "source": "website"
    },
    {
        "id": "68a924a64fe7a",
        "token": "452f83d3f7e46733836e8e3e1773eb57",
        "timestamp": "2025-08-23T02:16:43.315Z",
        "source": "shortlink",
        "uuid": "3dcd86bb-18e1-4d6a-ad60-6240d88e3bc6",
        "expires_at": "2025-08-23T04:16:43Z"
    },
    {
        "token": "fbdc5ef24a5aea9f9d99e131e52f6a0d",
        "timestamp": "2025-08-23T03:02:56Z",
        "uuid": "90e5ca1e-5cef-4e41-9390-068cb9514e32",
        "watch_time": 180,
        "video_id": "KnSsOhC6C34",
        "ip_address": "114.10.71.200",
        "user_agent": "Mozilla/5.0 (Linux; Android 10; K) AppleWebKit/537.36 (KHTML, like Gecko) Chrome/138.0.0.0 Mobile Safari/537.36",
        "pow_verified": true,
        "request_count": 0,
        "session_hash": "da7460a099efabc9d1e314a59f656bb3ee980a5a403e1b36a9c59ebd6f65dcf3",
        "id": "68a92f6126677",
        "source": "website"
    }
]