[
    {
        "id": "51e8ebacfd724",
        "token": "Uk7MsJvADapqz9BMTII7Cgp3Gc55n4",
        "timestamp": "2025-09-17T09:20:37Z",
        "source": "telegram",
        "uuid": "54ae05f3-1096-4303-b296-7702bfd5ae3c",
        "githubSignature": "5e5863d56defec7aeaa3ab9ed053d23e3cf91db4dc226d07f4e76ac9ccedd522"
    },
    {
        "id": "68ca89963a6e1",
        "token": "b63b538d0a949d38156059b36bf5fc81",
        "timestamp": "2025-09-17T10:12:28.939Z",
        "source": "shortlink",
        "uuid": "5bbb998d-64f6-4e4a-aa3b-3734ea7176b7",
        "expires_at": "2025-09-17T12:12:28Z"
    },
    {
        "token": "ccd7dfa55fea20cdd527058624c661c7",
        "timestamp": "2025-09-17T10:20:30Z",
        "uuid": "f32163b9-0252-4186-91ca-d70a0d2f6dfe",
        "watch_time": 300,
        "video_id": "C0368YioNAs",
        "ip_address": "112.215.230.158",
        "user_agent": "Mozilla/5.0 (Linux; Android 10; K) AppleWebKit/537.36 (KHTML, like Gecko) Chrome/137.0.0.0 Mobile Safari/537.36",
        "pow_verified": true,
        "request_count": 0,
        "session_hash": "d42d61b3fd9203e64c3db3d79f92acf49c986a125a4a5b5dc7f114dba4c0d672",
        "id": "68ca8b6ec51fb",
        "source": "website"
    },
    {
        "id": "68ca8c2aacfad",
        "token": "7233764a23add49e3e7e6c74c5edff75",
        "timestamp": "2025-09-17T10:23:29.743Z",
        "source": "shortlink",
        "uuid": "6536486f-9a5f-4cc5-9ef3-b4a80295c589",
        "expires_at": "2025-09-17T12:23:29Z"
    },
    {
        "token": "014674c90358f88ff327bdc84974d798",
        "timestamp": "2025-09-17T12:00:41Z",
        "uuid": "ff409457-3886-4c54-91c6-899247e20ae9",
        "watch_time": 120,
        "video_id": "ky2YLjJhEWs",
        "ip_address": "27.77.252.155",
        "user_agent": "Mozilla/5.0 (Windows NT 10.0; Win64; x64) AppleWebKit/537.36 (KHTML, like Gecko) Chrome/140.0.0.0 Safari/537.36",
        "pow_verified": true,
        "request_count": 0,
        "session_hash": "c95315e2844e1bc6e1e580b589efd061e1ae740f00d1c049446dd4bce39797f6",
        "id": "68caa2e9ef2f5",
        "source": "website"
    },
    {
        "token": "a521873cce50a8c22ccbaad05146616f",
        "timestamp": "2025-09-17T12:07:09Z",
        "uuid": "dd673019-2e74-4f57-9609-48c64265e255",
        "watch_time": 180,
        "video_id": "tQ3iTPxNO0U",
        "ip_address": "2404:c0:a701:3f08:a429:692f:b433:902",
        "user_agent": "Mozilla/5.0 (Linux; Android 10; K) AppleWebKit/537.36 (KHTML, like Gecko) Chrome/132.0.0.0 Mobile Safari/537.36",
        "pow_verified": true,
        "request_count": 0,
        "session_hash": "dab6da86318d64ec96f57f7d10832c0476874a2247af937d2540c35df8b88f0b",
        "id": "68caa46e1e029",
        "source": "website"
    }
]