[
  {
    "id": "687a3799355ef",
    "token": "HBWRSmpSrzxancYwxy7XSpr07RVnTG",
    "timestamp": "2025-07-18T12:01:28.160Z",
    "source": "website",
    "uuid": "5b48b499-ddc4-4a91-93c5-d6e6a6938911"
  },
  {
    "id": "687a3c3e67810",
    "token": "ba63ef28e7af11531b997848cbea5c58",
    "timestamp": "2025-07-18T12:21:02.507Z",
    "source": "shortlink",
    "uuid": "2722bd7b-bba5-41b0-9f98-e54a8a82d4d6",
    "expires_at": "2025-07-18T14:21:02Z"
  },
  {
    "id": "687a427c4b34a",
    "token": "911dbe319c2255f958725895f08015b6",
    "timestamp": "2025-07-18T12:47:35.869Z",
    "source": "shortlink",
    "uuid": "c3f3b0f3-e767-4647-892f-56e1f601a0c3",
    "expires_at": "2025-07-18T14:47:35Z"
  }
]
