[
  {
    "id": "67bd3688a613d",
    "token": "mzXHlVsL0DzWG6RCQLTmCjRJc0YgGj",
    "timestamp": "2025-02-25T03:18:31.880Z",
    "source": "website",
    "uuid": "fb0df6e2-3d13-400a-9296-01649e104d36"
  },
  {
    "id": "67bd3d595bcbe",
    "token": "eSn0jprNhmlqnRUoql174gEalcML3M",
    "timestamp": "2025-02-25T03:47:34.819Z",
    "source": "website",
    "uuid": "c4335dcd-0a7e-442c-9621-b598523f5247"
  },
  {
    "id": "67bd49e2cd33f",
    "token": "AwmIpG37rzCoOX1HdAYw7qa7QjKBxz",
    "timestamp": "2025-02-25T04:41:05.474Z",
    "source": "website",
    "uuid": "d618bb7f-2155-4437-8aa7-c90e18242e6c"
  }
]
