[
    {
        "token": "da4702ac27d4bb2c2f4a2848a85d4354",
        "timestamp": "2025-09-22T14:49:01Z",
        "uuid": "e0dc82fd-a360-4bd9-ba01-c93e8191f406",
        "watch_time": 300,
        "video_id": "JSGebCw9Ltc",
        "ip_address": "36.65.107.142",
        "user_agent": "Mozilla\/5.0 (Windows NT 10.0; Win64; x64) AppleWebKit\/537.36 (KHTML, like Gecko) Chrome\/140.0.0.0 Safari\/537.36",
        "pow_verified": true,
        "request_count": 0,
        "session_hash": "1a430b50eae583ce3fb810d5821c62819b370811101c7f203cc816b472a2dac3",
        "id": "68d161dd44631",
        "source": "website"
    },
    {
        "token": "260d90b257befabf89675529a20ff040",
        "timestamp": "2025-09-22T15:25:47Z",
        "uuid": "f16ae9f2-5ef4-4e2f-bbed-f23c21cccc79",
        "watch_time": 120,
        "video_id": "C0368YioNAs",
        "ip_address": "190.104.175.54",
        "user_agent": "Mozilla\/5.0 (Windows NT 10.0; Win64; x64) AppleWebKit\/537.36 (KHTML, like Gecko) Chrome\/140.0.0.0 Safari\/537.36",
        "pow_verified": true,
        "request_count": 0,
        "session_hash": "54ed8e08fb8cc234ee34f580672cdaf1ed8cd4c7775f17b1650de500523ff942",
        "id": "68d16a7c01c77",
        "source": "website"
    },
    {
        "id": "68d17353ce7a9",
        "token": "86c16610d48fd1b01bba2076cdce6ae5",
        "timestamp": "2025-09-22T16:03:19.193Z",
        "source": "shortlink",
        "uuid": "b6c20d85-f1bf-4bb4-bbe4-d875c2fd92a9",
        "expires_at": "2025-09-22T18:03:19Z"
    },
    {
        "id": "68d17eb603217",
        "token": "8897075da8148dec2d10ac1eac1c9ab1",
        "timestamp": "2025-09-22T16:51:58.597Z",
        "source": "shortlink",
        "uuid": "e4d4e050-2d11-4a8c-a75b-5b9a3a78a56d",
        "expires_at": "2025-09-22T18:51:58Z"
    },
    {
        "id": "68d18cb01ee9e",
        "token": "982330020c9e080009de04d7db02bda2",
        "timestamp": "2025-09-22T17:51:32.087Z",
        "source": "shortlink",
        "uuid": "64250e96-d7f2-4219-b88a-c4111c4914d8",
        "expires_at": "2025-09-22T19:51:32Z"
    }
]