[
    {
        "id": "686874c34bb8a",
        "token": "hpfrfGQcjp0SkZdM10Tkm77yDMxDrL",
        "timestamp": "2025-07-05T00:41:38.523Z",
        "source": "website",
        "uuid": "f30f1b6e-a205-4eb0-89b6-2ea6408368e4"
    },
    {
        "id": "00d8fce61ef74",
        "token": "7rbLFrqNDaChg91Vu410KHWagoqB3k",
        "timestamp": "2025-07-05T00:42:17Z",
        "source": "telegram",
        "uuid": "9aaf6524-4567-4788-9eb0-55f0d846015a",
        "githubSignature": "34627d1539869a630208a2b7ee6afdaee92d87f60535b708a7af4b7a2bdb60bb"
    },
    {
        "id": "6868750ad9452",
        "token": "5f47655e74a6a58fafc481aa626048d2",
        "timestamp": "2025-07-05T00:42:38.756Z",
        "source": "shortlink",
        "uuid": "d6c23b1f-95cf-477c-b45a-b947cd9e4b38",
        "expires_at": "2025-07-05T02:42:38Z"
    },
    {
        "id": "686878e55c0c1",
        "token": "wbx1V6MsDhNyxjxu25VxRsNdoH53ey",
        "timestamp": "2025-07-05T00:59:10.773Z",
        "source": "website",
        "uuid": "08907407-322f-4f9d-837e-994ec689aefb"
    },
    {
        "id": "68688279342e5",
        "token": "fd117fb14dd3361ea8c7bf6fff8b6291",
        "timestamp": "2025-07-05T01:40:25.788Z",
        "source": "shortlink",
        "uuid": "6cdfdd8a-3fad-44b5-91aa-38b0d4e12115",
        "expires_at": "2025-07-05T03:40:25Z"
    },
    {
        "id": "6868840e6226f",
        "token": "9NicfAPPGIuruPgAjRSVPIKgAoBgAE",
        "timestamp": "2025-07-05T01:46:53.531Z",
        "source": "website",
        "uuid": "e43ff4b5-47f0-4342-8691-60ea68642d08"
    },
    {
        "id": "6868843996b36",
        "token": "vaNCGxCCSR4jkQDvWsB1Yk3cYJtDN8",
        "timestamp": "2025-07-05T01:47:36.758Z",
        "source": "website",
        "uuid": "f5b886f1-9044-42c0-9af5-be35c7c25d97"
    },
    {
        "id": "6868845e47757",
        "token": "6YdgV4mqrfFdOc09KSMnsFN8rBrHk4",
        "timestamp": "2025-07-05T01:48:13.421Z",
        "source": "website",
        "uuid": "9ecdd3fb-7518-42c9-81c1-e5ce811bf945"
    },
    {
        "id": "68688497f31c8",
        "token": "EoxSYug4ydjjE3JCRXNntfMmIE7oxs",
        "timestamp": "2025-07-05T01:49:11.131Z",
        "source": "website",
        "uuid": "7e299645-8763-4770-919f-9b78fe5e7f3b"
    },
    {
        "id": "686884b19180e",
        "token": "aMrACnHp0B3XFoHYaAH4iLgiFQ0yxo",
        "timestamp": "2025-07-05T01:49:34.747Z",
        "source": "website",
        "uuid": "c0af8d14-ab49-488d-b1b5-a2e629b388c8"
    },
    {
        "id": "686884d389559",
        "token": "jjh3XxLNBlGZhumYsNJGQ3r3kPxD6N",
        "timestamp": "2025-07-05T01:50:10.608Z",
        "source": "website",
        "uuid": "2a8b8a5b-7d66-4fa4-848d-6d84adab0a49"
    },
    {
        "id": "6868853f4a713",
        "token": "gODNuUCESbru87yKoBv4rj9mhOGVdR",
        "timestamp": "2025-07-05T01:51:58.450Z",
        "source": "website",
        "uuid": "18506cef-7151-4a3c-8baf-e6446f41e898"
    }
]