[
  {
    "token": "6c0bce8a66bf5649a63b9100b066111b",
    "timestamp": "2025-10-05T13:52:37Z",
    "uuid": "f3253c39-871b-4bd8-842e-eb5a1efcf7eb",
    "watch_time": 240,
    "video_id": "JSGebCw9Ltc",
    "ip_address": "91.195.98.155",
    "user_agent": "Mozilla/5.0 (Linux; Android 10; K) AppleWebKit/537.36 (KHTML, like Gecko) Chrome/134.0.0.0 Mobile Safari/537.36 OPR/88.0.0.0",
    "pow_verified": true,
    "request_count": 0,
    "session_hash": "84feb522ad5376b1ed5e188b95dd1396037f9d9bfdd931d8efe24590f65a8a1e",
    "id": "68e278254038e",
    "source": "website"
  },
  {
    "id": "68e2842c42216",
    "token": "a35eef10934c3904155c99fe0ce5765a",
    "timestamp": "2025-10-05T14:43:10.434Z",
    "source": "shortlink",
    "uuid": "9e2a6784-21a3-4995-b741-37c644d18565",
    "expires_at": "2025-10-05T16:43:10Z"
  },
  {
    "id": "68e2855a72b4d",
    "token": "15f5b75364e522217e92320428968f25",
    "timestamp": "2025-10-05T14:48:33.605Z",
    "source": "shortlink",
    "uuid": "7f5fb12b-11a4-4c79-a8ae-e26a10978e95",
    "expires_at": "2025-10-05T16:48:33Z"
  },
  {
    "id": "68e285de3ac85",
    "token": "a009ebab340c56c7f8b4aa69e93a2c6c",
    "timestamp": "2025-10-05T14:50:41.125Z",
    "source": "shortlink",
    "uuid": "a23347b2-5781-4b0c-a64b-fe590b78b46f",
    "expires_at": "2025-10-05T16:50:41Z"
  },
  {
    "id": "68e287384e7c6",
    "token": "f8087477bc79684b286d43712f2d6f54",
    "timestamp": "2025-10-05T14:56:38.067Z",
    "source": "shortlink",
    "uuid": "ef5a9718-38bf-4756-a0ce-0382f9c790b7",
    "expires_at": "2025-10-05T16:56:38Z"
  }
]
