[
    {
        "token": "d8a09405b3d448a2f006c2ec299edff8",
        "timestamp": "2025-10-05T18:04:03Z",
        "uuid": "9b544153-a0bb-43b9-860f-f5942fb5f1fc",
        "watch_time": 180,
        "video_id": "C0368YioNAs",
        "ip_address": "197.39.134.72",
        "user_agent": "Mozilla\/5.0 (Linux; Android 10; K) AppleWebKit\/537.36 (KHTML, like Gecko) Chrome\/127.0.0.0 Mobile Safari\/537.36",
        "pow_verified": true,
        "request_count": 0,
        "session_hash": "631370cad350098d470bde0464c760eb23d445e13609dd365d8b6fcab10a4381",
        "id": "68e2b3141fbe2",
        "source": "website"
    },
    {
        "id": "f7dd174315024",
        "token": "l7jbBbGHQ25j5W7k0vzXhSrJyPHtAn",
        "timestamp": "2025-10-05T18:24:50Z",
        "source": "telegram",
        "uuid": "162b4564-0d58-4970-bb3b-ebd27b54b000",
        "githubSignature": "65e68fc2f006792619b5cdf2790d90674eb2785ba94f8ed7f3130d465e15129f"
    },
    {
        "id": "68e2bb5680970",
        "token": "d6c35f075f3460a69104ff562f21e172",
        "timestamp": "2025-10-05T18:38:53.247Z",
        "source": "shortlink",
        "uuid": "b42a1a2b-3551-404c-b44b-c8f75925bd5d",
        "expires_at": "2025-10-05T20:38:53Z"
    },
    {
        "id": "68e2d3dae7ed2",
        "token": "fb93ea2612bd53d62feba6333277f187",
        "timestamp": "2025-10-05T20:22:42.959Z",
        "source": "shortlink",
        "uuid": "f0081901-d171-46d4-bb40-383a59d94149",
        "expires_at": "2025-10-05T22:22:42Z"
    }
]