[
  {
    "token": "b8ea00cc41986569cc5d4317336c5630",
    "timestamp": "2025-10-07T10:56:18Z",
    "uuid": "6e360e9a-7aa3-46dd-8205-d8e2027afe2e",
    "watch_time": 240,
    "video_id": "JSGebCw9Ltc",
    "ip_address": "182.10.130.83",
    "user_agent": "Mozilla/5.0 (Linux; Android 10; K) AppleWebKit/537.36 (KHTML, like Gecko) Chrome/139.0.0.0 Mobile Safari/537.36",
    "pow_verified": true,
    "request_count": 0,
    "session_hash": "a2ca59828a6bb8b9d9b2574865da6a3949fc9945601b3b1eece6a3e1a767d3c4",
    "id": "68e4f1d2a8cd3",
    "source": "website"
  },
  {
    "id": "68e4fdf5a691a",
    "token": "8d7100eb05c379346d7584cb9f4fccfd",
    "timestamp": "2025-10-07T11:47:47.950Z",
    "source": "shortlink",
    "uuid": "ee773799-1db0-4f79-b885-3d9018684b1a",
    "expires_at": "2025-10-07T13:47:47Z"
  },
  {
    "token": "4192e982ab96fbf52c3b7f72a32b223a",
    "timestamp": "2025-10-07T12:37:54Z",
    "uuid": "7129660a-7b5e-43a9-a243-a72988bb4314",
    "watch_time": 180,
    "video_id": "tQ3iTPxNO0U",
    "ip_address": "27.75.230.29",
    "user_agent": "Mozilla/5.0 (Windows NT 10.0; Win64; x64) AppleWebKit/537.36 (KHTML, like Gecko) Chrome/140.0.0.0 Safari/537.36",
    "pow_verified": true,
    "request_count": 0,
    "session_hash": "2c730ecb60e5f231dbe4b7f2a3437737a520ddc4a71b418b102b2f1e070ec599",
    "id": "68e509a271da0",
    "source": "website"
  },
  {
    "id": "68e50a20cf2de",
    "token": "d581f7509b1f498416fc4eccd84a8f2f",
    "timestamp": "2025-10-07T12:39:40.840Z",
    "source": "shortlink",
    "uuid": "a9b7421b-df9f-4f98-a100-4a4c3a2c2832",
    "expires_at": "2025-10-07T14:39:40Z"
  },
  {
    "id": "68e50a8e34487",
    "token": "812cdaa29918036a2a9a18ee04f27782",
    "timestamp": "2025-10-07T12:41:03.420Z",
    "source": "shortlink",
    "uuid": "eb110ec9-0028-4491-bb93-9aab1e97307e",
    "expires_at": "2025-10-07T14:41:03Z"
  },
  {
    "id": "68e5127f9f6f1",
    "token": "b45d685659154c6053d13ae14219401e",
    "timestamp": "2025-10-07T13:15:26.075Z",
    "source": "shortlink",
    "uuid": "1c6e849c-45f3-4a24-b6e2-3302f434a894",
    "expires_at": "2025-10-07T15:15:26Z"
  },
  {
    "token": "987959d33d2e85f3cffe8fd5e0967b93",
    "timestamp": "2025-10-07T13:18:53Z",
    "uuid": "051414f0-93b1-4bc2-b242-efba7774f2e2",
    "watch_time": 300,
    "video_id": "tQ3iTPxNO0U",
    "ip_address": "190.53.167.89",
    "user_agent": "Mozilla/5.0 (Linux; Android 10; K) AppleWebKit/537.36 (KHTML, like Gecko) SamsungBrowser/28.0 Chrome/130.0.0.0 Mobile Safari/537.36",
    "pow_verified": true,
    "request_count": 0,
    "session_hash": "7cd122a74d471510da993bf1069d59f321124d2239f79ace8544515d7648d8c2",
    "id": "68e5133de0ab3",
    "source": "website"
  }
]
