[
    {
        "token": "71dacfda14477949c79ac969d47bb54e",
        "timestamp": "2025-10-10T08:48:43Z",
        "uuid": "a370d8bc-4530-44d7-8227-65db31a3b694",
        "watch_time": 240,
        "video_id": "C0368YioNAs",
        "ip_address": "202.10.40.199",
        "user_agent": "Mozilla\/5.0 (Linux; Android 10; K) AppleWebKit\/537.36 (KHTML, like Gecko) Chrome\/124.0.0.0 Mobile Safari\/537.36",
        "pow_verified": true,
        "request_count": 0,
        "session_hash": "f331a804e6e5eaa31a153d20a3712e0ca4826a01bbe159489074e9b51ed45e09",
        "id": "68e8c86b705c0",
        "source": "website"
    },
    {
        "token": "834b95af86d1ca28e967904cd3311630",
        "timestamp": "2025-10-10T09:04:20Z",
        "uuid": "0495ac21-cff0-4cd0-88bb-a8f29a29428c",
        "watch_time": 240,
        "video_id": "C0368YioNAs",
        "ip_address": "102.208.97.199",
        "user_agent": "Mozilla\/5.0 (Linux; Android 14; SM-A137F) AppleWebKit\/537.36 (KHTML, like Gecko) Chrome\/107.0.0.0 Mobile Safari\/537.36",
        "pow_verified": true,
        "request_count": 0,
        "session_hash": "c60e6305f1f1ce712c1595db20f9c4063aa203204681b92ce2fd4367dcef5d75",
        "id": "68e8cc14b1990",
        "source": "website"
    },
    {
        "id": "68e8cde6dfecc",
        "token": "380d8456ae5ea19ae16107c161de81b4",
        "timestamp": "2025-10-10T09:11:55.801Z",
        "source": "shortlink",
        "uuid": "7214dedd-0f7c-4268-a14a-a016df483ee7",
        "expires_at": "2025-10-10T11:11:55Z"
    },
    {
        "id": "dd1f0448eb5e4",
        "token": "oP2l9H5TTepUFnhgN2BletSZD1CaGj",
        "timestamp": "2025-10-10T09:21:06Z",
        "source": "telegram",
        "uuid": "b1935d84-a1b1-4aad-905e-6c41c9f83924",
        "githubSignature": "ddff36c60ad5f1eafd5843dcaf5fc50c810a3e227e38bf29c30d159a1f67fe97"
    },
    {
        "id": "68e8d2d4797f7",
        "token": "0993bd5ae62dd631aa3808a8c28d3140",
        "timestamp": "2025-10-10T09:32:48.994Z",
        "source": "shortlink",
        "uuid": "d4f2428b-8e75-4480-8134-9c0460dff2ca",
        "expires_at": "2025-10-10T11:32:48Z"
    },
    {
        "id": "68e8d4396c176",
        "token": "529c74b98657d71e0651a1e87bbbde1d",
        "timestamp": "2025-10-10T09:38:57.403Z",
        "source": "shortlink",
        "uuid": "56dc80f8-323e-4946-9f82-fd9dbc084ff4",
        "expires_at": "2025-10-10T11:38:57Z"
    },
    {
        "id": "68e8da13a8492",
        "token": "39b0bafea6556f3913e57e72a28b90f9",
        "timestamp": "2025-10-10T10:03:38.688Z",
        "source": "shortlink",
        "uuid": "af3b979d-1dd7-4dc7-a26d-983ce3a9af2f",
        "expires_at": "2025-10-10T12:03:38Z"
    },
    {
        "id": "68e8dcafdbedf",
        "token": "a80b4955a28dd4fb01e6ea2f4b121029",
        "timestamp": "2025-10-10T10:15:04.181Z",
        "source": "shortlink",
        "uuid": "9ca5f6bf-84d6-4bd9-9390-8c5acc2010f3",
        "expires_at": "2025-10-10T12:15:04Z"
    },
    {
        "id": "68e8e3222933a",
        "token": "ec8f5aa4b5ab24c54a581d80687b0e58",
        "timestamp": "2025-10-10T10:41:43.856Z",
        "source": "shortlink",
        "uuid": "c56d61b5-822f-4978-81a4-943cf27b21ef",
        "expires_at": "2025-10-10T12:41:43Z"
    },
    {
        "token": "10dbeb08a0a625f6979fdd39dc273289",
        "timestamp": "2025-10-10T10:44:05Z",
        "uuid": "e1a3eb82-f4ec-4ae3-86c9-b12c3eea4394",
        "watch_time": 120,
        "video_id": "ky2YLjJhEWs",
        "ip_address": "27.75.230.29",
        "user_agent": "Mozilla\/5.0 (Windows NT 10.0; Win64; x64) AppleWebKit\/537.36 (KHTML, like Gecko) Chrome\/140.0.0.0 Safari\/537.36",
        "pow_verified": true,
        "request_count": 0,
        "session_hash": "86c6b9c4d139238c44720dcbfd32c1ea1369c34ea687e9be6d6c9e15fba80aa4",
        "id": "68e8e3754fd76",
        "source": "website"
    },
    {
        "id": "68e8e41935d56",
        "token": "d589e761592b25ca2f94924e33583557",
        "timestamp": "2025-10-10T10:46:40.780Z",
        "source": "shortlink",
        "uuid": "9fb73623-af99-4aa5-8b30-0e9731015bab",
        "expires_at": "2025-10-10T12:46:40Z"
    },
    {
        "id": "68e8e42615fd7",
        "token": "5463e144fb7888d87f37d68dcac71f48",
        "timestamp": "2025-10-10T10:45:28.857Z",
        "source": "shortlink",
        "uuid": "c19733f6-c4df-4b10-ae97-d80e97d77e61",
        "expires_at": "2025-10-10T12:45:28Z"
    },
    {
        "id": "68e8e895225c4",
        "token": "d269062534f707629cada9be47a8aed2",
        "timestamp": "2025-10-10T11:05:46.870Z",
        "source": "shortlink",
        "uuid": "62a5e97c-7bb1-4480-8579-cb32c3d19517",
        "expires_at": "2025-10-10T13:05:46Z"
    }
]