[
    {
        "id": "2c92c7cea6284",
        "token": "girzi5xibkzh2YnbVRvkoNfAanAinl",
        "timestamp": "2025-08-09T18:11:53Z",
        "source": "telegram",
        "uuid": "275dc364-4668-4ea7-b70b-fc2105de4180",
        "githubSignature": "5e2f78049d4892d189df8788f251c55b1605e814e8c088d1ec6e7f59b5d22581"
    },
    {
        "token": "c230587c43c6ae8522b84fd0b79fad75",
        "timestamp": "2025-08-09T19:04:54Z",
        "uuid": "27e20fdd-e532-41fc-b6d4-3df11cc27ca0",
        "watch_time": 120,
        "video_id": "_dIJdN4QMJM",
        "ip_address": "2400:9800:a01:668f:25bf:17a9:3567:4ad6",
        "user_agent": "Mozilla/5.0 (Linux; Android 10; K) AppleWebKit/537.36 (KHTML, like Gecko) Chrome/137.0.0.0 Mobile Safari/537.36",
        "pow_verified": true,
        "request_count": 0,
        "session_hash": "55f3ec21cfcf647d81771ec4e0f062f0885d8eb47fdb937b4d7d901f0d72b7fd",
        "id": "68979bd6d45f1",
        "source": "website"
    },
    {
        "token": "e86a15fc49d9390b6c8db418bfbfbca8",
        "timestamp": "2025-08-09T19:07:56Z",
        "uuid": "b1111d5e-2b58-4133-8ad1-02b0aa03c1ce",
        "watch_time": 120,
        "video_id": "ky2YLjJhEWs",
        "ip_address": "2400:9800:a01:668f:25bf:17a9:3567:4ad6",
        "user_agent": "Mozilla/5.0 (Linux; Android 10; K) AppleWebKit/537.36 (KHTML, like Gecko) Chrome/137.0.0.0 Mobile Safari/537.36",
        "pow_verified": true,
        "request_count": 0,
        "session_hash": "90323168e7a666cfcf5c011a1eacdc5e86f4f4bd8c076c67d1902b6962682bea",
        "id": "68979c8d2973e",
        "source": "website"
    },
    {
        "token": "2e274551e0e87830d79c6f54cac34d44",
        "timestamp": "2025-08-09T19:48:22Z",
        "uuid": "7c00b51a-47c7-4491-9cbf-56ae89c488df",
        "watch_time": 300,
        "video_id": "tQ3iTPxNO0U",
        "ip_address": "2804:33cc:143e:6b00:68da:98cc:399:e521",
        "user_agent": "Mozilla/5.0 (Windows NT 10.0; Win64; x64) AppleWebKit/537.36 (KHTML, like Gecko) Chrome/138.0.0.0 Safari/537.36",
        "pow_verified": true,
        "request_count": 0,
        "session_hash": "650f2cc4b8c7be3c23b5bb7d172735a3c73256295a950b991fcef8dffdf10a35",
        "id": "6897a606ea6a7",
        "source": "website"
    },
    {
        "token": "3875d4dae47fb5e2f48e28ebaadb51c5",
        "timestamp": "2025-08-09T19:49:35Z",
        "uuid": "aeb2640b-dcd3-4e91-b4c8-0b82edc13e66",
        "watch_time": 240,
        "video_id": "tQ3iTPxNO0U",
        "ip_address": "102.90.81.104",
        "user_agent": "Mozilla/5.0 (Linux; Android 10; K) AppleWebKit/537.36 (KHTML, like Gecko) Chrome/138.0.0.0 Mobile Safari/537.36",
        "pow_verified": true,
        "request_count": 0,
        "session_hash": "7898ee197a76a0bf5ed4219d6612f6d6bc10e41210714d9a45dc1e8393853fa5",
        "id": "6897a64fa05f9",
        "source": "website"
    },
    {
        "token": "3b471a474f922ee8db1582360ce2aeed",
        "timestamp": "2025-08-09T19:52:47Z",
        "uuid": "a461d5d2-6f82-4f10-8705-a3dac7d1950c",
        "watch_time": 300,
        "video_id": "_dIJdN4QMJM",
        "ip_address": "2804:33cc:143e:6b00:68da:98cc:399:e521",
        "user_agent": "Mozilla/5.0 (Windows NT 10.0; Win64; x64) AppleWebKit/537.36 (KHTML, like Gecko) Chrome/138.0.0.0 Safari/537.36",
        "pow_verified": true,
        "request_count": 0,
        "session_hash": "31efe13580cf30aa4b80e6bbe5167b6593ffd8dbffe042bc0997bf815c568a06",
        "id": "6897a70f74465",
        "source": "website"
    },
    {
        "id": "6897ad9bf326f",
        "token": "12582f18810730ec27180cd0fd5fc744",
        "timestamp": "2025-08-09T20:20:29.022Z",
        "source": "shortlink",
        "uuid": "7a963146-a4c3-4e42-ab28-b36152b1b50c",
        "expires_at": "2025-08-09T22:20:29Z"
    },
    {
        "id": "6897ae0640235",
        "token": "c58070f6cf73dd2eb20ca28e6fc3a834",
        "timestamp": "2025-08-09T20:22:17.871Z",
        "source": "shortlink",
        "uuid": "0787b385-5155-44d5-b308-90b2bf539a82",
        "expires_at": "2025-08-09T22:22:17Z"
    },
    {
        "token": "083455121bdfc77a84762ed99bfbb6c0",
        "timestamp": "2025-08-09T20:52:50Z",
        "uuid": "65d95efe-b14a-4af4-b68f-a55f2b295e24",
        "watch_time": 180,
        "video_id": "_dIJdN4QMJM",
        "ip_address": "114.5.247.113",
        "user_agent": "Mozilla/5.0 (Linux; Android 10; K) AppleWebKit/537.36 (KHTML, like Gecko) Chrome/139.0.0.0 Mobile Safari/537.36",
        "pow_verified": true,
        "request_count": 0,
        "session_hash": "4696a8468b46e2c07f8c94c80bf656a47d6315fb4476493c641958e98364870b",
        "id": "6897b52275ed8",
        "source": "website"
    }
]