[
    {
        "id": "685c124fb72b3",
        "token": "13a04f5124d5ac4bb0ebea0f125870cb",
        "timestamp": "2025-06-25T15:14:05.279Z",
        "source": "shortlink",
        "uuid": "aaa7d863-4e15-43fe-b255-7a82a4e552d2",
        "expires_at": "2025-06-25T17:14:05Z"
    },
    {
        "id": "685c15547ff67",
        "token": "Md5wcsXtteg4KwwAMvcUsYYlnVnt4D",
        "timestamp": "2025-06-25T15:27:15.995Z",
        "source": "website",
        "uuid": "97e9bda6-ee33-4f85-80bf-a054415818d5"
    },
    {
        "id": "685c1dc588d25",
        "token": "cfCbWDgNQYRDighRnLiBupsC7NRcpp",
        "timestamp": "2025-06-25T16:03:10.780Z",
        "source": "website",
        "uuid": "44143707-a0a7-4324-a7ea-9d79c48ed4b8"
    },
    {
        "id": "685c27a3e4e23",
        "token": "oiM341GKuhjHKxPWXNAWjOcsdQB1nx",
        "timestamp": "2025-06-25T16:45:23.193Z",
        "source": "website",
        "uuid": "18b3a9b4-0ff8-40cc-89ea-11acbbc9d9ca"
    },
    {
        "id": "685c288777b28",
        "token": "mulu73428mix9wR1XNxbVLpy52sxm5",
        "timestamp": "2025-06-25T16:49:10.323Z",
        "source": "website",
        "uuid": "a79339ec-3d73-4b4a-9ad9-291e73187240"
    },
    {
        "id": "685c2ab7a9f10",
        "token": "3ju2QzFZ14giUagH9G0Pfsob8n77cE",
        "timestamp": "2025-06-25T16:58:29.623Z",
        "source": "website",
        "uuid": "34c021af-c0b9-43cb-99bb-82c3d3b77788"
    }
]