[
  {
    "id": "67bc9021d8c7c",
    "token": "dXRUgA3NM7tcVGWxHUwFIfw9PYAoAa",
    "timestamp": "2025-02-24T15:28:32.882Z",
    "source": "website",
    "uuid": "a393854e-642f-4fce-81f2-e55bf779cd4e",
    "githubSignature": "24c4d2a79bb2efc1402b1c414d732ce6f74bd898966f161c02ac16af65f4be26"
  },
  {
    "id": "67bc91155992e",
    "token": "faN8tDP5Vku3uvXYpcBKk0hUjUJqC1",
    "timestamp": "2025-02-24T15:32:35.391Z",
    "source": "website",
    "uuid": "c7cd7130-bebd-4caf-8aa2-8f6de362cba1"
  },
  {
    "id": "67bc91ede2484",
    "token": "vfqM8cbhx61F9PAeWoQlCPZ8Dk9Aos",
    "timestamp": "2025-02-24T15:36:12.044Z",
    "source": "website",
    "uuid": "02cc028d-d01b-4645-b0d2-5e251fdf035b"
  },
  {
    "id": "67bc95517aeb6",
    "token": "iSLOlbLG29xjR1KF3MVJUbJIM2Vd4G",
    "timestamp": "2025-02-24T15:50:36.970Z",
    "source": "website",
    "uuid": "a244f7cd-f3d2-497b-8c98-c6542ed14e26"
  },
  {
    "id": "67bc97fbf19de",
    "token": "mLCcWPKXfNcce31s5WcxDUIZT9Gl3e",
    "timestamp": "2025-02-24T16:02:02.423Z",
    "source": "website",
    "uuid": "4d8481e4-7e8e-4315-b2de-e114190ad780"
  },
  {
    "id": "67bc982914664",
    "token": "mLi0T0bdjAsNuSLhalg4m2Hu56S8MN",
    "timestamp": "2025-02-24T16:02:48.046Z",
    "source": "website",
    "uuid": "9414721a-0100-487b-a69a-ef52a4eb4175"
  },
  {
    "id": "67bc9a3e2da9b",
    "token": "MGca3yTwnkwtgYT497GggHhNNai1h7",
    "timestamp": "2025-02-24T16:11:41.566Z",
    "source": "website",
    "uuid": "1b91fc3a-f100-4702-8953-415a05db227e"
  }
]
