[
  {
    "id": "68b9bd5b07b49",
    "token": "f7dd9466fb077de41273141d9bc4f459",
    "timestamp": "2025-09-04T16:24:38.646Z",
    "source": "shortlink",
    "uuid": "ac132d54-1a57-4394-858f-05d3fdfaaaa2",
    "expires_at": "2025-09-04T18:24:38Z"
  },
  {
    "id": "68b9ca0d0d0ca",
    "token": "23a978a1cc853245681af13e2894c6b8",
    "timestamp": "2025-09-04T17:18:56.062Z",
    "source": "shortlink",
    "uuid": "f7d260b4-05e0-4386-8d52-e762ad2c288e",
    "expires_at": "2025-09-04T19:18:56Z"
  },
  {
    "id": "68b9cb7981973",
    "token": "9e0d26aff33a14b17ffceb81b289ffb8",
    "timestamp": "2025-09-04T17:25:05.883Z",
    "source": "shortlink",
    "uuid": "3b25e06d-d4d2-409e-955a-f3a4f24bb975",
    "expires_at": "2025-09-04T19:25:05Z"
  },
  {
    "id": "68b9cce38fccc",
    "token": "32fde2b6c87e7c0e02a0bec892007810",
    "timestamp": "2025-09-04T17:30:50.164Z",
    "source": "shortlink",
    "uuid": "3a71b4c0-0043-41f0-8812-b43f2314c2fa",
    "expires_at": "2025-09-04T19:30:50Z"
  },
  {
    "token": "1dae9ac27c8f268b942ea6efe6f3459b",
    "timestamp": "2025-09-04T17:41:54Z",
    "uuid": "6105f43f-3d7d-4686-a48c-5e481cd892c9",
    "watch_time": 180,
    "video_id": "tQ3iTPxNO0U",
    "ip_address": "2400:9800:11a:c15f:1862:23b0:920f:65dc",
    "user_agent": "Mozilla/5.0 (Linux; Android 10; K) AppleWebKit/537.36 (KHTML, like Gecko) Chrome/138.0.0.0 Mobile Safari/537.36",
    "pow_verified": true,
    "request_count": 0,
    "session_hash": "14d19503c243a03d9731305dddcc4ca79a944f2c3b49b5daccdcaba36fb21376",
    "id": "68b9cf6267189",
    "source": "website"
  }
]
