[
  {
    "id": "228eb484148c4",
    "token": "CNzomJc723qdV4n5taMzqzGAQk4vzj",
    "timestamp": "2025-10-02T18:27:46Z",
    "source": "telegram",
    "uuid": "7a7e5765-be41-4bdf-8bf8-3301a6516a52",
    "githubSignature": "f68151ea4b50d8ce8775898b924fd5d6713ec10694732bece49750474ae49d94"
  },
  {
    "token": "1f8ab46e76449214f3143c5ea0fba488",
    "timestamp": "2025-10-02T18:37:55Z",
    "uuid": "f45fdd8c-a8a7-4342-ac44-388fffa65e53",
    "watch_time": 240,
    "video_id": "ky2YLjJhEWs",
    "ip_address": "114.5.109.102",
    "user_agent": "Mozilla/5.0 (Linux; Android 11; vivo 1919 Build/RP1A.200720.012; wv) AppleWebKit/537.36 (KHTML, like Gecko) Version/4.0 Chrome/140.0.7339.207 Mobile Safari/537.36",
    "pow_verified": true,
    "request_count": 0,
    "session_hash": "138cec12dec9341194998cc83d52fb072fffa166c7c52f10dbc0490a4263508f",
    "id": "68dec683da34c",
    "source": "website"
  },
  {
    "id": "68ded7fd52432",
    "token": "4ffd072b7efc720832cc4bc4b3d83dbe",
    "timestamp": "2025-10-02T19:52:13.824Z",
    "source": "shortlink",
    "uuid": "1e378f51-ae63-41ba-b69c-fbeb5c88a99b",
    "expires_at": "2025-10-02T21:52:13Z"
  },
  {
    "id": "68dede4c828d1",
    "token": "6dfc707f4b17fc577327c7d16c863ba9",
    "timestamp": "2025-10-02T20:19:11.109Z",
    "source": "shortlink",
    "uuid": "05e45a01-1db0-4bb6-943d-97dbd28287c2",
    "expires_at": "2025-10-02T22:19:11Z"
  },
  {
    "id": "68dedf9c1b481",
    "token": "17a250db6eb60e9dc7b9a29ab2587670",
    "timestamp": "2025-10-02T20:24:51.508Z",
    "source": "shortlink",
    "uuid": "c1193593-7b2f-4eb7-bb3a-a4a857cf94bf",
    "expires_at": "2025-10-02T22:24:51Z"
  }
]
