[
    {
        "id": "686861fe8f3af",
        "token": "2cSBr1yV0wG93aI3VqqvzO66xHpz7z",
        "timestamp": "2025-07-04T23:21:33.195Z",
        "source": "website",
        "uuid": "9d5710a4-0c86-4da3-ba85-fa8a4c4492bd"
    },
    {
        "id": "686863f80e3a1",
        "token": "cjVBxL1etZkGSWwjjzYUd36pDoR77w",
        "timestamp": "2025-07-04T23:29:59.412Z",
        "source": "website",
        "uuid": "ad9e680d-81ed-4054-bbb9-5ca6303ef43a"
    },
    {
        "id": "6868642b85862",
        "token": "SGoc5z6mnZJgxnIAQNqnbcWTgFcR2S",
        "timestamp": "2025-07-04T23:30:50.944Z",
        "source": "website",
        "uuid": "496a2d37-9390-4da0-820d-4bfd8e0123ae"
    }
]