[
  {
    "token": "642cfaadb5de09473f8aab4de15a2104",
    "timestamp": "2025-10-13T12:32:19Z",
    "uuid": "351d06a3-e9c9-42b1-b66a-e32f143ac8bf",
    "watch_time": 60,
    "video_id": "C0368YioNAs",
    "ip_address": "2405:8180:901:301a:cb:826e:35ae:234d",
    "user_agent": "Mozilla/5.0 (Linux; Android 10; K) AppleWebKit/537.36 (KHTML, like Gecko) Chrome/124.0.0.0 Mobile Safari/537.36",
    "pow_verified": true,
    "request_count": 0,
    "session_hash": "5ef97bcee807a10dd32b213054600491b81153d421acff4b6893afa8cce40830",
    "id": "68ecf1542790f",
    "source": "website"
  },
  {
    "id": "68ed0b2fbdbe9",
    "token": "d227da9ff3dac33d30985314ba819992",
    "timestamp": "2025-10-13T14:22:29.711Z",
    "source": "shortlink",
    "uuid": "e2cee233-e68f-4d22-969b-c884df2ad5e6",
    "expires_at": "2025-10-13T16:22:29Z"
  },
  {
    "id": "68ed0c87e5a8e",
    "token": "85f6df40161adeba3b7c67fb10596b8e",
    "timestamp": "2025-10-13T14:28:10.674Z",
    "source": "shortlink",
    "uuid": "8c7a8786-ea37-45b8-b551-ed6b347f05eb",
    "expires_at": "2025-10-13T16:28:10Z"
  },
  {
    "id": "68ed0de0d49fa",
    "token": "e930e4bf12092f7f3b13bc39be66a6d2",
    "timestamp": "2025-10-13T14:33:42.990Z",
    "source": "shortlink",
    "uuid": "c18fb49e-2c2b-4025-b612-4a5efb02b7db",
    "expires_at": "2025-10-13T16:33:42Z"
  },
  {
    "id": "68ed11034ad3d",
    "token": "d1eadac78452946a978c4ef4ec1c8e21",
    "timestamp": "2025-10-13T14:47:12.649Z",
    "source": "shortlink",
    "uuid": "3ceb3d87-3c64-448f-ae7a-5a48198c90bd",
    "expires_at": "2025-10-13T16:47:12Z"
  },
  {
    "token": "8a45ac961ec011c18a55b37a14585ef2",
    "timestamp": "2025-10-13T14:49:06Z",
    "uuid": "0cb70b37-aa44-425e-81e8-0344b9fbbf2e",
    "watch_time": 60,
    "video_id": "C0368YioNAs",
    "ip_address": "27.75.230.29",
    "user_agent": "Mozilla/5.0 (Windows NT 10.0; Win64; x64) AppleWebKit/537.36 (KHTML, like Gecko) Chrome/141.0.0.0 Safari/537.36",
    "pow_verified": true,
    "request_count": 0,
    "session_hash": "1f550648e0177a0a8462318cef0cb49eeed10340c974bb80ad4d746e98990232",
    "id": "68ed1162affd5",
    "source": "website"
  },
  {
    "token": "feb3918bee36ce44537e646f4b7f8e05",
    "timestamp": "2025-10-13T14:50:37Z",
    "uuid": "6192eebb-b280-4948-91be-5d3a45b4981d",
    "watch_time": 60,
    "video_id": "JSGebCw9Ltc",
    "ip_address": "103.172.197.15",
    "user_agent": "Mozilla/5.0 (Windows NT 10.0; Win64; x64) AppleWebKit/537.36 (KHTML, like Gecko) Chrome/141.0.0.0 Safari/537.36",
    "pow_verified": true,
    "request_count": 0,
    "session_hash": "81727c91ded810721d6ce92b02a215f25f7f9b9a5e24801159434f9add167f54",
    "id": "68ed11bd4e01f",
    "source": "website"
  },
  {
    "id": "68ed13ad201dd",
    "token": "35ff8f4a8d578ad871f8f542cbefedbb",
    "timestamp": "2025-10-13T14:58:40.318Z",
    "source": "shortlink",
    "uuid": "7ca678da-a829-4718-b59a-bfe6761daa86",
    "expires_at": "2025-10-13T16:58:40Z"
  },
  {
    "id": "68ed1728421ab",
    "token": "684ccf59e0a33aed320e39f020b9b44e",
    "timestamp": "2025-10-13T15:13:34.151Z",
    "source": "shortlink",
    "uuid": "6db32da0-83d8-40cd-affc-66f211960390",
    "expires_at": "2025-10-13T17:13:34Z"
  },
  {
    "id": "68ed17cd49400",
    "token": "3c8ef8b75f08c6f7548829304e3b97dd",
    "timestamp": "2025-10-13T15:16:18.433Z",
    "source": "shortlink",
    "uuid": "44255bef-d949-44f8-94c3-563372c4c483",
    "expires_at": "2025-10-13T17:16:18Z"
  }
]
