[
  {
    "id": "6848125c2f65c",
    "token": "HiCphmx0ifwE2zAwrWGnA8HGihfESa",
    "timestamp": "2025-06-10T11:09:15.196Z",
    "source": "website",
    "uuid": "03e886f9-8b55-4479-b67f-38350fe49d71"
  },
  {
    "id": "6848153822e08",
    "token": "qEBtpDLhBzlgpp8rF0t84LH0VSSdrY",
    "timestamp": "2025-06-10T11:21:24.654Z",
    "source": "website",
    "uuid": "7ab8c437-4045-4b20-8096-3d4e9f5b108a"
  },
  {
    "id": "684817f5773e5",
    "token": "j3R1KOd2k1DkTupcg9ypwP0Z6rVshq",
    "timestamp": "2025-06-10T11:33:06.033Z",
    "source": "website",
    "uuid": "f2d5e961-a752-4a9c-9590-d05f3b4bf0be"
  }
]
