[
    {
        "id": "677f266a3b026",
        "token": "2qlwjN191WnjblwTjMC2JeVgYFvRcx",
        "timestamp": "2025-01-09T01:29:10.874Z"
    },
    {
        "id": "677f2a2bcc522",
        "token": "R5geE5DydfN1jQYpaQJaLEhHT25xkc",
        "timestamp": "2025-01-09T01:45:13.995Z"
    },
    {
        "id": "677f2c7d3b1d4",
        "token": "ftHC9hEQAQaUCJARljhJ5v2gEr4bK3",
        "timestamp": "2025-01-09T01:55:07.326Z"
    },
    {
        "id": "677f2f0caf952",
        "token": "Af3xaCfuueMIVwbAnA4GmAxFnNpCtQ",
        "timestamp": "2025-01-09T02:06:03.026Z"
    }
]