[
    {
        "token": "81cca1bea222b1a8690aaa09cc3f457d",
        "timestamp": "2025-10-08T08:53:24Z",
        "uuid": "44778a7f-fa0d-4a9d-9ff7-dd5eaf9feb58",
        "watch_time": 300,
        "video_id": "JSGebCw9Ltc",
        "ip_address": "2401:4900:22e5:c71:1:0:caa1:46fa",
        "user_agent": "Mozilla\/5.0 (Linux; Android 10; K) AppleWebKit\/537.36 (KHTML, like Gecko) Chrome\/139.0.0.0 Mobile Safari\/537.36",
        "pow_verified": true,
        "request_count": 0,
        "session_hash": "9ce9f654e4898d9e2e8bb118d982ac41549e8c208647e3d6de58efc79d6a4ffe",
        "id": "68e62684c493b",
        "source": "website"
    },
    {
        "id": "4806d32149ba4",
        "token": "4iRqtGFTWNQdv7CzerUw3XbTK7QoYV",
        "timestamp": "2025-10-08T09:21:01Z",
        "source": "telegram",
        "uuid": "34ab2201-93e7-4572-8204-e9d949013030",
        "githubSignature": "f9f42b7c7e097e6939cbbc81713a06fc9e8b5e2a342837792e7fb1054c6f4980"
    },
    {
        "id": "68e62d23b18e7",
        "token": "219226977d8632b616a51d7f28e7e444",
        "timestamp": "2025-10-08T09:20:55.200Z",
        "source": "shortlink",
        "uuid": "9a7e4bfd-27e1-45db-9db5-6bc48dff6e35",
        "expires_at": "2025-10-08T11:20:55Z"
    },
    {
        "token": "db8f1a3f0780581cb514f0e9fe7d08b3",
        "timestamp": "2025-10-08T09:25:39Z",
        "uuid": "b74b23eb-6c6f-46af-9e94-6135d965db6d",
        "watch_time": 120,
        "video_id": "ky2YLjJhEWs",
        "ip_address": "27.75.230.29",
        "user_agent": "Mozilla\/5.0 (Windows NT 10.0; Win64; x64) AppleWebKit\/537.36 (KHTML, like Gecko) Chrome\/140.0.0.0 Safari\/537.36",
        "pow_verified": true,
        "request_count": 0,
        "session_hash": "d4daef505ea16a6ed5ed7cce65c4ff77478b5f961b3a1b43ce01a523bb794892",
        "id": "68e62e138d4ae",
        "source": "website"
    },
    {
        "token": "4194be4380ba0a95173b3ca3396ba9a7",
        "timestamp": "2025-10-08T09:37:57Z",
        "uuid": "0c69ea43-b7e2-4f91-ac2d-554379821ae5",
        "watch_time": 180,
        "video_id": "C0368YioNAs",
        "ip_address": "202.51.197.156",
        "user_agent": "Mozilla\/5.0 (Linux; Android 10; K) AppleWebKit\/537.36 (KHTML, like Gecko) Chrome\/139.0.0.0 Mobile Safari\/537.36",
        "pow_verified": true,
        "request_count": 0,
        "session_hash": "3b54b4f2ebc4b23e3cae7e962532fe0d59e797a39e2f9864f7a4b51bf5d5ca16",
        "id": "68e630f5d0ab0",
        "source": "website"
    },
    {
        "id": "68e63bcaad89d",
        "token": "0a4a729a768c69a08d93d1db6160650c",
        "timestamp": "2025-10-08T10:23:58.579Z",
        "source": "shortlink",
        "uuid": "5359c775-de57-42e1-a431-c3735ac60941",
        "expires_at": "2025-10-08T12:23:58Z"
    },
    {
        "token": "9cd05529afb7e7b8568f14bc953aca74",
        "timestamp": "2025-10-08T10:35:17Z",
        "uuid": "0c2be976-5e85-481b-b059-f755ccef6338",
        "watch_time": 120,
        "video_id": "JSGebCw9Ltc",
        "ip_address": "202.51.197.156",
        "user_agent": "Mozilla\/5.0 (Linux; Android 10; K) AppleWebKit\/537.36 (KHTML, like Gecko) Chrome\/139.0.0.0 Mobile Safari\/537.36",
        "pow_verified": true,
        "request_count": 0,
        "session_hash": "bda61e5984008cb0b224a6699d19b720485d98b32f35c1526951cf2867256bbf",
        "id": "68e63e65848b7",
        "source": "website"
    },
    {
        "token": "94afb42b2336d5deca41ee5c02e0ede3",
        "timestamp": "2025-10-08T11:15:58Z",
        "uuid": "92f38d9e-04a1-4a2c-b350-fbcd86f6ff4a",
        "watch_time": 180,
        "video_id": "JSGebCw9Ltc",
        "ip_address": "2401:4900:22e5:c71:1:0:caa1:46fa",
        "user_agent": "Mozilla\/5.0 (Linux; Android 10; K) AppleWebKit\/537.36 (KHTML, like Gecko) Chrome\/139.0.0.0 Mobile Safari\/537.36",
        "pow_verified": true,
        "request_count": 0,
        "session_hash": "1616f2db9fcdd23766a6a318130e20b114ea0084fb979d092a43f5f88e3c84d3",
        "id": "68e647ee52966",
        "source": "website"
    },
    {
        "id": "68e6497b235dc",
        "token": "620fa7c228117fb85947af27fdcd8ae7",
        "timestamp": "2025-10-08T11:22:27.563Z",
        "source": "shortlink",
        "uuid": "07d18dba-9758-48f3-9be1-4ec27a04ed22",
        "expires_at": "2025-10-08T13:22:27Z"
    }
]