[
  {
    "id": "690a3e9ecc915",
    "token": "13f4a74c9677c5fd42b159985aa87e3b",
    "timestamp": "2025-11-04T17:57:37.924Z",
    "source": "shortlink",
    "uuid": "6ca23e7e-effb-4331-9699-b5ae00bdb614",
    "expires_at": "2025-11-04T19:57:37Z"
  },
  {
    "id": "690a3ee2592db",
    "token": "b2ff96a94c068346d7fae51b593cf570",
    "timestamp": "2025-11-04T17:58:46.647Z",
    "source": "shortlink",
    "uuid": "9763481d-bd0c-48c5-8f12-03707ca99b90",
    "expires_at": "2025-11-04T19:58:46Z"
  },
  {
    "id": "a2f22db131514",
    "token": "DAydUAxe1YHpMiJiQoRSqMNOmB3Mgi",
    "timestamp": "2025-11-04T18:30:00Z",
    "source": "telegram",
    "uuid": "c06e36f0-d5ea-44f8-973c-fd071c64b0fe",
    "githubSignature": "5b87702270be64d7bd9b823f53f7a87dc6e90855b8d8827370a8aff8a118a9c7"
  },
  {
    "id": "690a580daf6f8",
    "token": "3e2b80b71613fa206bd1bc88e7050fde",
    "timestamp": "2025-11-04T19:46:09.131Z",
    "source": "shortlink",
    "uuid": "40b692cb-5d29-4597-8072-f909c53671d4",
    "expires_at": "2025-11-04T21:46:09Z"
  },
  {
    "id": "690a58ab6bf4f",
    "token": "1483ed0bb5e87ee6a8c1bf690c66d88b",
    "timestamp": "2025-11-04T19:48:48.408Z",
    "source": "shortlink",
    "uuid": "fe92461f-b5fd-478f-aee1-c9842d7f4c5e",
    "expires_at": "2025-11-04T21:48:48Z"
  }
]
