[
  {
    "id": "687646b7a7be4",
    "token": "lUQIEJNKjKWcOkdUXO106vKqSqpa3i",
    "timestamp": "2025-07-15T12:16:52.850Z",
    "source": "website",
    "uuid": "ceedbe6a-98fa-41fc-b9a6-b76cc86806b4"
  },
  {
    "id": "687652011dd59",
    "token": "4ff3374a83e2f73fc0ac48fed3835339",
    "timestamp": "2025-07-15T13:04:55.768Z",
    "source": "shortlink",
    "uuid": "134efc34-f396-4eb6-bdf5-bac1f899e20a",
    "expires_at": "2025-07-15T15:04:55Z"
  },
  {
    "id": "687653396960f",
    "token": "43e8eb55a635a9c89d023e55f532b3cd",
    "timestamp": "2025-07-15T13:10:07.572Z",
    "source": "shortlink",
    "uuid": "6e399eb3-2b86-4de9-b3ad-378a132b3d1f",
    "expires_at": "2025-07-15T15:10:07Z"
  },
  {
    "id": "6876589d94c71",
    "token": "TiXtvS6Tz4BT6VPyuDKzztiBBjIFHS",
    "timestamp": "2025-07-15T13:33:09.097Z",
    "source": "website",
    "uuid": "e2e27192-a9e0-4c45-8cea-a47c47606ead"
  },
  {
    "id": "687659e9756e4",
    "token": "eh8DbkaZ3qUn9Ts1xctKRydVooGT18",
    "timestamp": "2025-07-15T13:38:29.097Z",
    "source": "website",
    "uuid": "b3026f40-665b-41ca-8992-0257ee4365c6"
  }
]
