[
    {
        "token": "2e446ae05d45431e1a398f7e613d966c",
        "timestamp": "2025-09-01T17:09:50Z",
        "uuid": "8fade3dc-c095-4909-aeaa-07312f5c9ad0",
        "watch_time": 120,
        "video_id": "KnSsOhC6C34",
        "ip_address": "110.138.87.135",
        "user_agent": "Mozilla/5.0 (Linux; Android 10; K) AppleWebKit/537.36 (KHTML, like Gecko) Chrome/139.0.0.0 Mobile Safari/537.36",
        "pow_verified": true,
        "request_count": 0,
        "session_hash": "b31375cece7c737724f820d0ffdbb06b5a0d11f7143b1891d032f85a50ed2b7e",
        "id": "68b5d35e7360b",
        "source": "website"
    },
    {
        "id": "68b5e21b30b9e",
        "token": "664c36514ac7314ea2d694e47f49597b",
        "timestamp": "2025-09-01T18:12:26.638Z",
        "source": "shortlink",
        "uuid": "7ca5b85e-9d00-4897-9ca3-705c7d7b401c",
        "expires_at": "2025-09-01T20:12:26Z"
    },
    {
        "id": "21ef9e1d13504",
        "token": "WkifsC9DC1M8IgS8JreuGQwlbcZEDQ",
        "timestamp": "2025-09-01T18:26:55Z",
        "source": "telegram",
        "uuid": "0ea1c167-b9da-481e-958c-564b85cf6eca",
        "githubSignature": "1c4775bb8722febf9d9541111c32c06efb4e900e87b4157c005bfed9a369e286"
    },
    {
        "id": "68b5e5dd0954f",
        "token": "678b571177ffa3a4d0349e9ebd538182",
        "timestamp": "2025-09-01T18:28:36.425Z",
        "source": "shortlink",
        "uuid": "5a5a6762-cd8e-452a-904b-8f6c72e445d7",
        "expires_at": "2025-09-01T20:28:36Z"
    },
    {
        "token": "40da0272c2a5fdee22040158845f7712",
        "timestamp": "2025-09-01T18:35:50Z",
        "uuid": "d8e41920-69fc-4f79-b94a-b0d2ab3b87c5",
        "watch_time": 240,
        "video_id": "JSGebCw9Ltc",
        "ip_address": "103.172.116.88",
        "user_agent": "Mozilla/5.0 (Linux; Android 10; K) AppleWebKit/537.36 (KHTML, like Gecko) Chrome/138.0.0.0 Mobile Safari/537.36",
        "pow_verified": true,
        "request_count": 0,
        "session_hash": "f9e6eb51ed671a6ba1f1f3adb7574d66bb37e286c6f186599c707c4770809646",
        "id": "68b5e786658ca",
        "source": "website"
    },
    {
        "token": "924a0c2f7b968aae1d61e3ce6b0a072b",
        "timestamp": "2025-09-01T19:35:53Z",
        "uuid": "4b10dd00-2d40-45d7-9cb0-4a08cc48e9bc",
        "watch_time": 180,
        "video_id": "ky2YLjJhEWs",
        "ip_address": "2806:265:1400:e39:e8bf:8d83:ffc9:a4c3",
        "user_agent": "Mozilla/5.0 (Linux; Android 10; K) AppleWebKit/537.36 (KHTML, like Gecko) Chrome/138.0.0.0 Mobile Safari/537.36",
        "pow_verified": true,
        "request_count": 0,
        "session_hash": "e271c5697c7888035069d7839439175da68bdddaa0bcde151ec8d597a3b2db59",
        "id": "68b5f59943b61",
        "source": "website"
    },
    {
        "token": "ef6b7fb238a4891f38f45a15750802b1",
        "timestamp": "2025-09-01T19:46:49Z",
        "uuid": "c241ecf9-af4a-4b2c-8ab2-c76ef9cf7ea4",
        "watch_time": 240,
        "video_id": "JSGebCw9Ltc",
        "ip_address": "2400:9800:aa1:b1e9:37ae:4a26:4c53:656",
        "user_agent": "Mozilla/5.0 (Linux; Android 10; K) AppleWebKit/537.36 (KHTML, like Gecko) Chrome/139.0.0.0 Mobile Safari/537.36",
        "pow_verified": true,
        "request_count": 0,
        "session_hash": "09295a8aa345dc1fc58292157d69c2544b290efed45c1af085327f07c24b7291",
        "id": "68b5f829e5dae",
        "source": "website"
    }
]