[
    {
        "id": "68530f84c0d90",
        "token": "f957713be1a667783b1db3ee2e9da393",
        "timestamp": "2025-06-18T19:11:34.614Z",
        "source": "shortlink",
        "uuid": "bbefca19-7225-4f90-8f1c-ab53df50122b",
        "expires_at": "2025-06-19T01:11:34Z"
    },
    {
        "id": "68531e62477d1",
        "token": "51646c80f8d4516ae378f7469f556bdf",
        "timestamp": "2025-06-18T20:15:11.435Z",
        "source": "shortlink",
        "uuid": "d3a46bdc-3ae7-461d-9fee-918aea23b037",
        "expires_at": "2025-06-19T02:15:11Z"
    },
    {
        "id": "68531ea76b6f5",
        "token": "42f9d73974e3e9d229ac4baef1f5ab73",
        "timestamp": "2025-06-18T20:16:18.962Z",
        "source": "shortlink",
        "uuid": "65c08186-ccc9-43c4-b264-1a1e5292de14",
        "expires_at": "2025-06-19T02:16:18Z"
    },
    {
        "id": "68531eee6bd9c",
        "token": "7455d841a4a8e1a633078d3aeab86bb7",
        "timestamp": "2025-06-18T20:17:34.487Z",
        "source": "shortlink",
        "uuid": "67b50645-82e5-4156-bbb3-9f5e29e3439f",
        "expires_at": "2025-06-19T02:17:34Z"
    },
    {
        "id": "68534a0134214",
        "token": "SyBfqyZfj7b4rUrM4FxIyVeZW1fmVk",
        "timestamp": "2025-06-18T23:21:29.788Z",
        "source": "website",
        "uuid": "2430fb68-9ba3-468f-b49b-ed3619a76589"
    },
    {
        "id": "68534b6e9a839",
        "token": "E5EbB7a03UsgBD3eI5wgdNU2VxKv0f",
        "timestamp": "2025-06-18T23:27:41.671Z",
        "source": "website",
        "uuid": "4e39e865-eb3c-42cb-bdfe-f47060d44d61"
    },
    {
        "id": "68534b99c8a56",
        "token": "46ac1a639e72dd5e66fb3aac9e0265c2",
        "timestamp": "2025-06-18T23:28:16.526Z",
        "source": "shortlink",
        "uuid": "dfbd3b99-c8cf-48d5-b06f-b6314dc6e8f1",
        "expires_at": "2025-06-19T05:28:16Z"
    },
    {
        "id": "68534c787d91c",
        "token": "15a8dda1890cfdb83107293972269f63",
        "timestamp": "2025-06-18T23:31:59.575Z",
        "source": "shortlink",
        "uuid": "e660d873-5aef-4cd5-b3da-b8b7dc0e68fe",
        "expires_at": "2025-06-19T05:31:59Z"
    },
    {
        "id": "68534c9eb3668",
        "token": "7df8b3a64aec41fed5f9e59d2627bc62",
        "timestamp": "2025-06-18T23:32:39.384Z",
        "source": "shortlink",
        "uuid": "6ab31f48-f996-40e6-b27c-3eccf7194ff5",
        "expires_at": "2025-06-19T05:32:39Z"
    },
    {
        "id": "68534d90476fd",
        "token": "f70c65e5d9d9b67a9b858c4fb66c4c7d",
        "timestamp": "2025-06-18T23:36:40.000Z",
        "source": "shortlink",
        "uuid": "1e9723f2-bd77-4ba8-ba6c-0163580a5065",
        "expires_at": "2025-06-19T05:36:40Z"
    },
    {
        "id": "68534e81825b8",
        "token": "e858dba0a5da5184080f02d8fead171c",
        "timestamp": "2025-06-18T23:40:35.943Z",
        "source": "shortlink",
        "uuid": "9f1d8dc2-201c-4c89-80c2-4bed1e76b363",
        "expires_at": "2025-06-19T05:40:35Z"
    },
    {
        "id": "6853526b32b5a",
        "token": "a01ba905e7c13d01b5eac825e5b72d70",
        "timestamp": "2025-06-18T23:57:22.237Z",
        "source": "shortlink",
        "uuid": "f8679108-b7a3-4660-acaa-6e07d3e3f8b7",
        "expires_at": "2025-06-19T05:57:22Z"
    }
]