[
    {
        "id": "68965d93bdcfc",
        "token": "fdcbc9757ec50c5b376b009bcb73a276",
        "timestamp": "2025-08-08T20:26:52.851Z",
        "source": "shortlink",
        "uuid": "6273d86d-7aa6-4164-bf35-38bd77b44fe1",
        "expires_at": "2025-08-08T22:26:52Z"
    },
    {
        "id": "689669411cf5c",
        "token": "226e0e6018b86dc9f112760428a43ea8",
        "timestamp": "2025-08-08T21:16:39.606Z",
        "source": "shortlink",
        "uuid": "5054acfe-3b35-49ec-848c-62e88d6685fb",
        "expires_at": "2025-08-08T23:16:39Z"
    },
    {
        "id": "68966ba909108",
        "token": "25cb23ada700ee81fe1d0e8a7e108eb2",
        "timestamp": "2025-08-08T21:26:55.916Z",
        "source": "shortlink",
        "uuid": "2dee1bca-dfff-40c3-9300-c9e75e83509d",
        "expires_at": "2025-08-08T23:26:55Z"
    },
    {
        "id": "68966c861f394",
        "token": "2bd1684e464d29c0e72704c6ec0456f6",
        "timestamp": "2025-08-08T21:30:21.811Z",
        "source": "shortlink",
        "uuid": "edc0e5b0-2b72-4c2f-b17e-991f9a141d7a",
        "expires_at": "2025-08-08T23:30:21Z"
    },
    {
        "id": "6896706de23b5",
        "token": "30a3567e68f5fd6757526c03f6529476",
        "timestamp": "2025-08-08T21:47:16.628Z",
        "source": "shortlink",
        "uuid": "c43ed243-f75d-44c5-8dcf-237ce57330ae",
        "expires_at": "2025-08-08T23:47:16Z"
    },
    {
        "id": "689670fd9f52b",
        "token": "834b8f1201be29a68e23d9606abce858",
        "timestamp": "2025-08-08T21:49:41.796Z",
        "source": "shortlink",
        "uuid": "26e8565b-8a40-4967-9845-555e72fe6537",
        "expires_at": "2025-08-08T23:49:41Z"
    },
    {
        "id": "6896724827074",
        "token": "191082d582ba6df3af6739b3f808fe8e",
        "timestamp": "2025-08-08T21:55:07.644Z",
        "source": "shortlink",
        "uuid": "44ec076b-4c5c-4b54-9461-58c835b51aba",
        "expires_at": "2025-08-08T23:55:07Z"
    },
    {
        "id": "6896729ad3ff3",
        "token": "d6e146bd3fb0143826cdd93f5a61f892",
        "timestamp": "2025-08-08T21:56:21.910Z",
        "source": "shortlink",
        "uuid": "5826870f-deea-496e-91ad-4e738a93280d",
        "expires_at": "2025-08-08T23:56:21Z"
    },
    {
        "id": "689679163f52b",
        "token": "ca11ecb650cc6ca399a02f0611deaccf",
        "timestamp": "2025-08-08T22:24:13.185Z",
        "source": "shortlink",
        "uuid": "13a3425d-a0ca-4efd-8621-281b6a2ea84b",
        "expires_at": "2025-08-09T00:24:13Z"
    }
]