[
    {
        "token": "db3978d905950945456c112d619961f6",
        "timestamp": "2025-08-16T20:46:15Z",
        "uuid": "4d44ea78-58ce-4b80-9bd3-06a5a629e2d7",
        "watch_time": 240,
        "video_id": "ky2YLjJhEWs",
        "ip_address": "110.138.80.73",
        "user_agent": "Mozilla/5.0 (Linux; Android 10; K) AppleWebKit/537.36 (KHTML, like Gecko) Chrome/139.0.0.0 Mobile Safari/537.36",
        "pow_verified": true,
        "request_count": 0,
        "session_hash": "1821d0e344a5b8abb28e1e20b319d2ea63b8f83c00324f71feb0e6d649b6c8ff",
        "id": "68a0ee1837630",
        "source": "website"
    },
    {
        "token": "2005ae9668c8758eff89e68e5b958ba8",
        "timestamp": "2025-08-16T21:04:34Z",
        "uuid": "64fd5696-be5f-4bad-922b-3287be12d0c0",
        "watch_time": 300,
        "video_id": "KnSsOhC6C34",
        "ip_address": "41.139.46.139",
        "user_agent": "Mozilla/5.0 (Windows NT 10.0; Win64; x64) AppleWebKit/537.36 (KHTML, like Gecko) Chrome/139.0.0.0 Safari/537.36 Edg/139.0.0.0",
        "pow_verified": true,
        "request_count": 0,
        "session_hash": "42145b9ed91caf841d926da9f89f46a530472ab599b11d9fdefbb789452e705b",
        "id": "68a0f2623ed29",
        "source": "website"
    },
    {
        "token": "2513aa84b4c92a73d0044727a09189c5",
        "timestamp": "2025-08-16T23:28:56Z",
        "uuid": "9124bf04-a4e0-4b71-a492-db8a17c3e0f5",
        "watch_time": 180,
        "video_id": "ky2YLjJhEWs",
        "ip_address": "103.153.66.164",
        "user_agent": "Mozilla/5.0 (Linux; Android 10; K) AppleWebKit/537.36 (KHTML, like Gecko) Chrome/138.0.0.0 Mobile Safari/537.36",
        "pow_verified": true,
        "request_count": 0,
        "session_hash": "17263cbd653ea63da82d4316b96d7c2e6f21acad502d26eb2074cb877fd9347d",
        "id": "68a114385f25e",
        "source": "website"
    }
]