[
    {
        "id": "6865dd02cb60f",
        "token": "d8U3mvrLlpRSeipA4dvZ9KL73HJDUW",
        "timestamp": "2025-07-03T01:29:37.065Z",
        "source": "website",
        "uuid": "2bc36515-8c7c-48f7-9e36-6380861b8d43"
    },
    {
        "id": "6865e52939040",
        "token": "UZthmmQ6rOKkeV7XXHqosMGkadnr1K",
        "timestamp": "2025-07-03T02:04:25.870Z",
        "source": "website",
        "uuid": "d49fc438-ad50-4770-a828-d41abf0b1dc2"
    },
    {
        "id": "6865eb428a153",
        "token": "KBUwApkiXlpX8zwP8eQhu3GViEHUho",
        "timestamp": "2025-07-03T02:30:25.848Z",
        "source": "website",
        "uuid": "813c8d47-ef3e-4615-a48c-d9048385a712"
    },
    {
        "id": "6865f0014ec9d",
        "token": "089233848de1f56d104c8ffb49e52425",
        "timestamp": "2025-07-03T02:50:16.624Z",
        "source": "shortlink",
        "uuid": "cc97d8af-77d0-44c0-9f1f-2868094f0cc8",
        "expires_at": "2025-07-03T04:50:16Z"
    },
    {
        "id": "6865f0d134a38",
        "token": "d654942c710c1162aa01ee6145a60437",
        "timestamp": "2025-07-03T02:54:00.705Z",
        "source": "shortlink",
        "uuid": "5721fad8-e3f6-4b6a-9489-af8e035e8071",
        "expires_at": "2025-07-03T04:54:00Z"
    },
    {
        "id": "6865f85f0fcc4",
        "token": "BtzFoFWm45KjWIKKyMtZI8LyhATD4f",
        "timestamp": "2025-07-03T03:26:21.375Z",
        "source": "website",
        "uuid": "c651ae9a-6963-4c82-8501-04b902efe7d5"
    }
]